pytbd/__init__.py
pytbd/__main__.py
pytbd-0.0.3.dist-info/LICENSE
pytbd-0.0.3.dist-info/METADATA
pytbd-0.0.3.dist-info/WHEEL
pytbd-0.0.3.dist-info/entry_points.txt
pytbd-0.0.3.dist-info/top_level.txt
pytbd-0.0.3.dist-info/RECORD
