Metadata-Version: 2.1
Name: pytbd
Version: 0.0.3
Summary: Swiss army knife for Apple's .tbd file manipulation
Home-page: https://github.com/doronz88/pytbd
Author: DoronZ
License: UNKNOWN
Project-URL: pytbd, https://github.com/doronz88/pytbd
Platform: UNKNOWN
Classifier: Programming Language :: Python :: 3.6
Classifier: Programming Language :: Python :: 3.7
Classifier: Programming Language :: Python :: 3.8
Classifier: Programming Language :: Python :: 3.9
Classifier: Programming Language :: Python :: 3.10
License-File: LICENSE
Requires-Dist: click
Requires-Dist: pyyaml
Requires-Dist: pygments
Requires-Dist: coloredlogs
